Workbook

Sheet Leggimi
A1: MACRO'S — Modello finanziario di lancio e validazione
A2: Versione del 12/10/2026. Tutte le cifre sono stime di pianificazione da sostituire con preventivi reali.
A4: Come usarlo
A5: 1. Modifica solo le celle in BLU nel foglio 'Ipotesi' (le leve principali hanno anche lo sfondo GIALLO).
A6: 2. I fogli 'Fase 0-1', 'Ghost Kitchen', 'Ristorante' e 'Capitale a rischio' si ricalcolano da soli.
A7: 3. Nel foglio 'Stage gate' inserisci i valori reali (colonna gialla): l'esito dice se passare alla fase successiva.
A9: Legenda colori
A10: Testo blu = input modificabile · Testo nero = formula · Testo verde = collegamento da un altro foglio · Sfondo giallo = ipotesi chiave / da compilare
A12: Fonti usate per le ipotesi
A13: Commissioni delivery 25–35% con consegna della piattaforma: Gambero Rosso, gamberorosso.it/notizie/quanto-costa-il-food-delivery-ai-ristoranti-conviene-davvero/ ; Fooderise, fooderise.com/en/platform-fees
A14: Investimento ristorante in Italia 60.000–120.000 €, oltre 300.000 € per format strutturati in zone centrali: trend-online.com/economia/quanti-soldi-servono-per-aprire-un-ristorante/
A15: Scontrino medio e prezzi: listino per 100 g del totem MACRO'S (index.html del repository).
A16: Canoni, stipendi, lavori: stime da validare con preventivi su Milano.

Sheet Capitale a rischio
A1: Fase | B1: Durata | C1: Capitale a rischio (€) | D1: Cumulato (€) | E1: Si finanzia con | F1: Si sblocca se
A2: 0 — Preparazione | B2: 2–4 settimane | C2: ='Fase 0-1'!$C$11 -> 4000 | D2: =SUM($C$2:C2) -> 4000 | E2: Capitale dei fondatori | F2: —
A3: 1 — Annuncio + Early Access | B3: 6–8 settimane | C3: ='Fase 0-1'!$C$12 -> 5600 | D3: =SUM($C$2:C3) -> 9600 | E3: Capitale dei fondatori | F3: Fase 0 completata
A4: 2 — Ghost Kitchen Milano | B4: 6 mesi | C4: ='Ghost Kitchen'!$B$29 -> 70551.682 | D4: =SUM($C$2:C4) -> 80151.682 | E4: Fondatori + prevendite Founding Member | F4: Stage gate 1 superato
A5: 3 — Primo ristorante Milano | B5: 4–6 mesi di cantiere | C5: =Ristorante!$B$10 -> 392400 | D5: =SUM($C$2:C5) -> 472551.68 | E5: Fondatori + soci/investitori + finanziamento | F5: Stage gate 2 superato
A6: 4a — Ghost Kitchen città 2 | B6: 6 mesi | C6: ='Ghost Kitchen'!$B$29*Ipotesi!$B$38 -> 70551.682 | D6: =SUM($C$2:C6) -> 543103.36 | E6: Cassa generata + investitori | F6: Stage gate 3 superato
A7: 4b — Secondo store Milano | B7: 4–6 mesi | C7: =Ristorante!$B$10*Ipotesi!$B$39 -> 353160 | D7: =SUM($C$2:C7) -> 896263.36 | E7: Cassa generata + finanziamento | F7: Primo store sopra il pareggio da 3 mesi
A9: Capitale a rischio prima della prova di domanda pagante (Fasi 0–2) | C9: =D4 -> 80151.682
A10: Stessa cifra al netto delle prevendite Founding Member | C10: =D4-'Fase 0-1'!$C$13 -> 67901.682

Sheet Ipotesi
A1: Ipotesi | B1: Valore | C1: Unità | D1: Nota / fonte
A2: Prezzi e margini
A3: Scontrino medio delivery (IVA inclusa) | B3: 13.5 | C3: €/ordine | D3: Bowl tipo: base + proteina + topping dal listino per 100 g del totem
A4: Scontrino medio in negozio (IVA inclusa) | B4: 13 | C4: €/ordine | D4: Senza packaging delivery
A5: IVA ristorazione | B5: 0.1 | C5: % | D5: Aliquota 10% su somministrazione e asporto
A6: Food cost | B6: 0.32 | C6: % ricavi netti | D6: Obiettivo; da verificare con le schede ricetta
A7: Packaging per ordine delivery/asporto | B7: 0.6 | C7: €/ordine | D7: Contenitore, posate, sacchetto
A8: Canali di vendita (Ghost Kitchen)
A9: Quota ordini via piattaforme | B9: 0.7 | C9: % | D9: Il resto passa da app MACRO'S / ritiro
A10: Commissione piattaforme | B10: 0.3 | C10: % ricavi | D10: Range 25–35% con consegna della piattaforma (Gambero Rosso, Fooderise)
A11: Costo pagamento canale proprio | B11: 0.03 | C11: % ricavi | D11: Carte / Stripe; consegna con rider esterno esclusa
A12: Fase 0-1: Early Access
A13: Prezzo pacchetto Founding Member | B13: 49 | C13: € | D13: 5 pasti + priorità + 10% a vita; rimborsabile se la città non apre in 4 mesi
A14: Founding Member venduti (obiettivo) | B14: 250 | C14: persone | D14: 18% degli iscritti della prima città
A15: Ghost Kitchen Milano: costi fissi mensili
A16: Canone cucina condivisa (utenze incluse) | B16: 3500 | C16: €/mese | D16: Stima; chiedere preventivi a operatori di cucine condivise a Milano
A17: Personale (2,5 FTE) | B17: 7500 | C17: €/mese | D17: Costo azienda
A18: Marketing locale e promo piattaforme | B18: 1500 | C18: €/mese
A19: Software, consulenze, varie | B19: 400 | C19: €/mese
A20: Giorni di apertura al mese | B20: 30 | C20: giorni
A21: Ghost Kitchen Milano: ordini al giorno (rampa)
A22: Mese 1 | B22: 35 | C22: ordini/giorno
A23: Mese 2 | B23: 50 | C23: ordini/giorno
A24: Mese 3 | B24: 65 | C24: ordini/giorno
A25: Mese 4 | B25: 80 | C25: ordini/giorno
A26: Mese 5 | B26: 90 | C26: ordini/giorno
A27: Mese 6 | B27: 100 | C27: ordini/giorno
A28: Ristorante Milano (80–100 m², 40 coperti)
A29: Ordini in negozio al giorno (a regime) | B29: 180 | C29: ordini/giorno | D29: Pranzo + cena, totem
A30: Ordini delivery al giorno (a regime) | B30: 80 | C30: ordini/giorno | D30: Clienti spostati dalla Ghost Kitchen
A31: Affitto locale | B31: 6000 | C31: €/mese | D31: Zona semicentrale; stima
A32: Personale (10 FTE) | B32: 32000 | C32: €/mese | D32: Costo azienda
A33: Utenze | B33: 2500 | C33: €/mese
A34: Marketing | B34: 2500 | C34: €/mese
A35: Manutenzione, software, varie | B35: 2000 | C35: €/mese
A36: Imprevisti su investimenti | B36: 0.1 | C36: %
A37: Replica
A38: Ghost Kitchen in una nuova città | B38: 1 | C38: x costo GK Milano | D38: Stesso modello, costi simili
A39: Ristorante aggiuntivo | B39: 0.9 | C39: x costo ristorante Milano | D39: Progetto e fornitori già pronti

Sheet Fase 0-1
A1: Fase | B1: Voce | C1: Costo (€) | D1: Nota
A2: Fase 0 | B2: Landing Early Access + dominio | C2: 300 | D2: Landing già nel repository; dominio e hosting
A3: Fase 0 | B3: Deposito marchio UIBM (3 classi) + consulente | C3: 1200
A4: Fase 0 | B4: Shooting foto/video prodotti | C4: 1500
A5: Fase 0 | B5: Avvio social e grafiche | C5: 600
A6: Fase 0 | B6: Consulenza contratto Steven Basalari | C6: 400 | D6: Accordo a equity/revenue share: nessuna fee fissa
A7: Fase 1 | B7: Tasting day Milano (cucina a ore + 200 bowl) | C7: 1800
A8: Fase 1 | B8: Sponsorizzazione dei contenuti migliori | C8: 2500 | D8: Solo sui post che performano meglio in organico
A9: Fase 1 | B9: Strumenti (email, sondaggi, pagamenti) | C9: 300
A10: Fase 1 | B10: Imprevisti | C10: 1000
B11: Costo Fase 0 | C11: =SUMIFS(C2:C10,A2:A10,"Fase 0") -> 4000
B12: Costo Fase 1 | C12: =SUMIFS(C2:C10,A2:A10,"Fase 1") -> 5600
B13: Incasso prevendite Founding Member (anticipo, non ricavo) | C13: =Ipotesi!$B$13*Ipotesi!$B$14 -> 12250 | D13: Va restituito in pasti: riduce la cassa da anticipare, non il costo

Sheet Ghost Kitchen
A1: Investimento iniziale Ghost Kitchen
A2: Attrezzature aggiuntive (abbattitore, piastre, contenitori) | B2: 12000
A3: SCIA, HACCP, consulenze | B3: 3000
A4: Packaging brandizzato (primo stock) | B4: 2000
A5: Foto e menu per le piattaforme | B5: 1500
A6: Deposito cauzionale (2 mesi) | B6: 7000
A7: Imprevisti | B7: =SUM(B2:B6)*Ipotesi!$B$36 -> 2550
A8: Totale investimento iniziale | B8: =SUM(B2:B7) -> 28050
A10: Conto economico mensile (6 mesi di test)
A11: Voce | B11: Mese 1 | C11: Mese 2 | D11: Mese 3 | E11: Mese 4 | F11: Mese 5 | G11: Mese 6 | H11: Totale 6 mesi
A12: Ordini al giorno | B12: =Ipotesi!$B$22 -> 35 | C12: =Ipotesi!$B$23 -> 50 | D12: =Ipotesi!$B$24 -> 65 | E12: =Ipotesi!$B$25 -> 80 | F12: =Ipotesi!$B$26 -> 90 | G12: =Ipotesi!$B$27 -> 100
A13: Ordini al mese | B13: =B12*Ipotesi!$B$20 -> 1050 | C13: =C12*Ipotesi!$B$20 -> 1500 | D13: =D12*Ipotesi!$B$20 -> 1950 | E13: =E12*Ipotesi!$B$20 -> 2400 | F13: =F12*Ipotesi!$B$20 -> 2700 | G13: =G12*Ipotesi!$B$20 -> 3000 | H13: =SUM(B13:G13) -> 12600
A14: Ricavi netti (IVA esclusa) | B14: =B13*Ipotesi!$B$3/(1+Ipotesi!$B$5) -> 12886.364 | C14: =C13*Ipotesi!$B$3/(1+Ipotesi!$B$5) -> 18409.091 | D14: =D13*Ipotesi!$B$3/(1+Ipotesi!$B$5) -> 23931.818 | E14: =E13*Ipotesi!$B$3/(1+Ipotesi!$B$5) -> 29454.545 | F14: =F13*Ipotesi!$B$3/(1+Ipotesi!$B$5) -> 33136.364 | G14: =G13*Ipotesi!$B$3/(1+Ipotesi!$B$5) -> 36818.182 | H14: =SUM(B14:G14) -> 154636.36
A15: Food cost | B15: =-B14*Ipotesi!$B$6 -> -4123.6364 | C15: =-C14*Ipotesi!$B$6 -> -5890.9091 | D15: =-D14*Ipotesi!$B$6 -> -7658.1818 | E15: =-E14*Ipotesi!$B$6 -> -9425.4545 | F15: =-F14*Ipotesi!$B$6 -> -10603.636 | G15: =-G14*Ipotesi!$B$6 -> -11781.818 | H15: =SUM(B15:G15) -> -49483.636
A16: Commissioni piattaforme e pagamenti | B16: =-B14*(Ipotesi!$B$9*Ipotesi!$B$10+(1-Ipotesi!$B$9)*Ipotesi!$B$11) -> -2822.1136 | C16: =-C14*(Ipotesi!$B$9*Ipotesi!$B$10+(1-Ipotesi!$B$9)*Ipotesi!$B$11) -> -4031.5909 | D16: =-D14*(Ipotesi!$B$9*Ipotesi!$B$10+(1-Ipotesi!$B$9)*Ipotesi!$B$11) -> -5241.0682 | E16: =-E14*(Ipotesi!$B$9*Ipotesi!$B$10+(1-Ipotesi!$B$9)*Ipotesi!$B$11) -> -6450.5455 | F16: =-F14*(Ipotesi!$B$9*Ipotesi!$B$10+(1-Ipotesi!$B$9)*Ipotesi!$B$11) -> -7256.8636 | G16: =-G14*(Ipotesi!$B$9*Ipotesi!$B$10+(1-Ipotesi!$B$9)*Ipotesi!$B$11) -> -8063.1818 | H16: =SUM(B16:G16) -> -33865.364
A17: Packaging | B17: =-B13*Ipotesi!$B$7 -> -630 | C17: =-C13*Ipotesi!$B$7 -> -900 | D17: =-D13*Ipotesi!$B$7 -> -1170 | E17: =-E13*Ipotesi!$B$7 -> -1440 | F17: =-F13*Ipotesi!$B$7 -> -1620 | G17: =-G13*Ipotesi!$B$7 -> -1800 | H17: =SUM(B17:G17) -> -7560
A18: Margine di contribuzione | B18: =SUM(B14:B17) -> 5310.6136 | C18: =SUM(C14:C17) -> 7586.5909 | D18: =SUM(D14:D17) -> 9862.5682 | E18: =SUM(E14:E17) -> 12138.545 | F18: =SUM(F14:F17) -> 13655.864 | G18: =SUM(G14:G17) -> 15173.182 | H18: =SUM(B18:G18) -> 63727.364
A19: Costi fissi (canone, personale, marketing, varie) | B19: =-(Ipotesi!$B$16+Ipotesi!$B$17+Ipotesi!$B$18+Ipotesi!$B$19) -> -12900 | C19: =-(Ipotesi!$B$16+Ipotesi!$B$17+Ipotesi!$B$18+Ipotesi!$B$19) -> -12900 | D19: =-(Ipotesi!$B$16+Ipotesi!$B$17+Ipotesi!$B$18+Ipotesi!$B$19) -> -12900 | E19: =-(Ipotesi!$B$16+Ipotesi!$B$17+Ipotesi!$B$18+Ipotesi!$B$19) -> -12900 | F19: =-(Ipotesi!$B$16+Ipotesi!$B$17+Ipotesi!$B$18+Ipotesi!$B$19) -> -12900 | G19: =-(Ipotesi!$B$16+Ipotesi!$B$17+Ipotesi!$B$18+Ipotesi!$B$19) -> -12900 | H19: =SUM(B19:G19) -> -77400
A20: Risultato operativo del mese | B20: =B18+B19 -> -7589.3864 | C20: =C18+C19 -> -5313.4091 | D20: =D18+D19 -> -3037.4318 | E20: =E18+E19 -> -761.45455 | F20: =F18+F19 -> 755.86364 | G20: =G18+G19 -> 2273.1818 | H20: =SUM(B20:G20) -> -13672.636
A21: Cassa cumulata (dopo investimento iniziale) | B21: =-'Ghost Kitchen'!$B$8+B20 -> -35639.386 | C21: =B21+C20 -> -40952.795 | D21: =C21+D20 -> -43990.227 | E21: =D21+E20 -> -44751.682 | F21: =E21+F20 -> -43995.818 | G21: =F21+G20 -> -41722.636
A23: Indicatori
A24: Margine di contribuzione per ordine (€) | B24: =IFERROR(H18/H13,0) -> 5.0577273
A25: Margine di contribuzione (% ricavi) | B25: =IFERROR(H18/H14,0) -> 0.41211111
A26: Ordini al giorno per il pareggio | B26: =IFERROR((Ipotesi!$B$16+Ipotesi!$B$17+Ipotesi!$B$18+Ipotesi!$B$19)/'Ghost Kitchen'!$B$24/Ipotesi!$B$20,0) -> 85.018424
A27: Massimo fabbisogno di cassa (€) | B27: =-MIN(B21:G21) -> 44751.682
A28: Riserva di cassa consigliata: 2 mesi di costi fissi (€) | B28: =2*(Ipotesi!$B$16+Ipotesi!$B$17+Ipotesi!$B$18+Ipotesi!$B$19) -> 25800
A29: Capitale da mettere a rischio nella Fase 2 (€) | B29: ='Ghost Kitchen'!$B$27+'Ghost Kitchen'!$B$28 -> 70551.682
A30: di cui coperto dalle prevendite Founding Member (€) | B30: ='Fase 0-1'!$C$13 -> 12250

Sheet Ristorante
A1: Investimento ristorante Milano
A2: Lavori e arredo (80–100 m²) | B2: 120000
A3: Cucina e attrezzature | B3: 60000
A4: Totem MACRO'S (3 postazioni, hardware) | B4: 9000
A5: Progetto, licenze, SCIA | B5: 12000
A6: Deposito cauzionale (3 mesi) | B6: 18000
A7: Pre-apertura: stock, formazione, marketing | B7: 15000
A8: Imprevisti | B8: =SUM(B2:B7)*Ipotesi!$B$36 -> 23400
A9: Riserva: 3 mesi di costi fissi | B9: =3*(Ipotesi!$B$31+Ipotesi!$B$32+Ipotesi!$B$33+Ipotesi!$B$34+Ipotesi!$B$35) -> 135000
A10: Totale capitale ristorante | B10: =SUM(B2:B9) -> 392400
A12: Conto economico mensile a regime
A13: Voce | B13: €/mese | C13: % ricavi
A14: Ricavi netti in negozio | B14: =Ipotesi!$B$29*Ipotesi!$B$4/(1+Ipotesi!$B$5)*Ipotesi!$B$20 -> 63818.182 | C14: =IFERROR(B14/B$16,0) -> 0.68421053
A15: Ricavi netti delivery | B15: =Ipotesi!$B$30*Ipotesi!$B$3/(1+Ipotesi!$B$5)*Ipotesi!$B$20 -> 29454.545 | C15: =IFERROR(B15/B$16,0) -> 0.31578947
A16: Ricavi netti totali | B16: =B14+B15 -> 93272.727 | C16: =IFERROR(B16/B$16,0) -> 1
A17: Food cost | B17: =-B16*Ipotesi!$B$6 -> -29847.273 | C17: =IFERROR(B17/B$16,0) -> -0.32
A18: Commissioni delivery | B18: =-B15*(Ipotesi!$B$9*Ipotesi!$B$10+(1-Ipotesi!$B$9)*Ipotesi!$B$11) -> -6450.5455 | C18: =IFERROR(B18/B$16,0) -> -0.069157895
A19: Packaging delivery | B19: =-Ipotesi!$B$30*Ipotesi!$B$20*Ipotesi!$B$7 -> -1440 | C19: =IFERROR(B19/B$16,0) -> -0.015438596
A20: Personale | B20: =-Ipotesi!$B$32 -> -32000 | C20: =IFERROR(B20/B$16,0) -> -0.34307992
A21: Affitto | B21: =-Ipotesi!$B$31 -> -6000 | C21: =IFERROR(B21/B$16,0) -> -0.064327485
A22: Utenze, marketing, varie | B22: =-(Ipotesi!$B$33+Ipotesi!$B$34+Ipotesi!$B$35) -> -7000 | C22: =IFERROR(B22/B$16,0) -> -0.075048733
A23: EBITDA mensile | B23: =SUM(B16:B22) -> 10534.909 | C23: =IFERROR(B23/B$16,0) -> 0.11294737
A25: Ordini totali al giorno per il pareggio | B25: =IFERROR((Ipotesi!$B$31+Ipotesi!$B$32+Ipotesi!$B$33+Ipotesi!$B$34+Ipotesi!$B$35)/((B16+B17+B18+B19)/((Ipotesi!$B$29+Ipotesi!$B$30)*Ipotesi!$B$20))/Ipotesi!$B$20,0) -> 210.6783
A26: Rientro dell'investimento (mesi a regime) | B26: =IFERROR(IF(B23<=0,"mai",Ristorante!$B$10/B23),0) -> 37.247592

Sheet Stage gate
A1: Gate | B1: Indicatore | C1: Direzione | D1: Soglia | E1: Valore reale | F1: Esito
A2: 1 · Early Access → Ghost Kitchen | B2: Iscritti Early Access totali | C2: >= | D2: 3000 | F2: =IF(E2="","da misurare",IF(OR(AND(C2=">=",E2>=D2),AND(C2="<=",E2<=D2)),"OK","NO")) -> da misurare
A3: 1 · Early Access → Ghost Kitchen | B3: Iscritti nella prima città | C3: >= | D3: 1000 | F3: =IF(E3="","da misurare",IF(OR(AND(C3=">=",E3>=D3),AND(C3="<=",E3<=D3)),"OK","NO")) -> da misurare
A4: 1 · Early Access → Ghost Kitchen | B4: Founding Member prepagati nella prima città | C4: >= | D4: 200 | F4: =IF(E4="","da misurare",IF(OR(AND(C4=">=",E4>=D4),AND(C4="<=",E4<=D4)),"OK","NO")) -> da misurare
A5: 1 · Early Access → Ghost Kitchen | B5: Iscritti che dichiarano 2+ pasti a settimana | C5: >= | D5: 0.35 | F5: =IF(E5="","da misurare",IF(OR(AND(C5=">=",E5>=D5),AND(C5="<=",E5<=D5)),"OK","NO")) -> da misurare
A6: 1 · Early Access → Ghost Kitchen | B6: Costo per iscritto (€) | C6: <= | D6: 2 | F6: =IF(E6="","da misurare",IF(OR(AND(C6=">=",E6>=D6),AND(C6="<=",E6<=D6)),"OK","NO")) -> da misurare
A7: 2 · Ghost Kitchen → Ristorante | B7: Ordini al giorno, media del mese 6 | C7: >= | D7: 100 | F7: =IF(E7="","da misurare",IF(OR(AND(C7=">=",E7>=D7),AND(C7="<=",E7<=D7)),"OK","NO")) -> da misurare
A8: 2 · Ghost Kitchen → Ristorante | B8: Clienti che riordinano entro 30 giorni | C8: >= | D8: 0.35 | F8: =IF(E8="","da misurare",IF(OR(AND(C8=">=",E8>=D8),AND(C8="<=",E8<=D8)),"OK","NO")) -> da misurare
A9: 2 · Ghost Kitchen → Ristorante | B9: Voto medio sulle piattaforme | C9: >= | D9: 4.6 | F9: =IF(E9="","da misurare",IF(OR(AND(C9=">=",E9>=D9),AND(C9="<=",E9<=D9)),"OK","NO")) -> da misurare
A10: 2 · Ghost Kitchen → Ristorante | B10: Margine di contribuzione per ordine (€) | C10: >= | D10: 5 | F10: =IF(E10="","da misurare",IF(OR(AND(C10=">=",E10>=D10),AND(C10="<=",E10<=D10)),"OK","NO")) -> da misurare
A11: 2 · Ghost Kitchen → Ristorante | B11: Quota ordini dal canale proprio (app/ritiro) | C11: >= | D11: 0.3 | F11: =IF(E11="","da misurare",IF(OR(AND(C11=">=",E11>=D11),AND(C11="<=",E11<=D11)),"OK","NO")) -> da misurare
A12: 2 · Ghost Kitchen → Ristorante | B12: Ordini concentrati in un raggio di 2 km | C12: >= | D12: 0.4 | F12: =IF(E12="","da misurare",IF(OR(AND(C12=">=",E12>=D12),AND(C12="<=",E12<=D12)),"OK","NO")) -> da misurare
A13: 3 · Ristorante → Replica | B13: Mesi consecutivi sopra il pareggio | C13: >= | D13: 3 | F13: =IF(E13="","da misurare",IF(OR(AND(C13=">=",E13>=D13),AND(C13="<=",E13<=D13)),"OK","NO")) -> da misurare
... A15: 3 · Ristorante → Replica | B15: Iscritti Early Access nella città successiva | C15: >= | D15: 1000 | F15: =IF(E15="","da misurare",IF(OR(AND(C15=">=",E15>=D15),AND(C15="<=",E15<=D15)),"OK","NO")) -> da misurare
A17: 1 · Early Access → Ghost Kitchen | B17: Decisione | F17: =IF(COUNTIFS(A2:A15,A17,F2:F15,"NO")>0,"STOP o correggi",IF(COUNTIFS(A2:A15,A17,F2:F15,"da misurare")>0,"in corso","AVANTI")) -> in corso
A18: 2 · Ghost Kitchen → Ristorante | B18: Decisione | F18: =IF(COUNTIFS(A2:A15,A18,F2:F15,"NO")>0,"STOP o correggi",IF(COUNTIFS(A2:A15,A18,F2:F15,"da misurare")>0,"in corso","AVANTI")) -> in corso
A19: 3 · Ristorante → Replica | B19: Decisione | F19: =IF(COUNTIFS(A2:A15,A19,F2:F15,"NO")>0,"STOP o correggi",IF(COUNTIFS(A2:A15,A19,F2:F15,"da misurare")>0,"in corso","AVANTI")) -> in corso
A21: Compila la colonna gialla con i dati reali. Un solo NO blocca il gate: correggi e rimisura prima di investire.
